dicksonui/Application.py
dicksonui/Control.py
dicksonui/DicksonUI.js
dicksonui/__init__.py
dicksonui/bom.py
dicksonui/builtins.py
dicksonui/dom.py
dicksonui/errors.py
dicksonui/fakeattr.py
dicksonui/index.html
dicksonui/jslib.py
dicksonui/template.py
dicksonui/var.py
DicksonUI-2.4.5.dist-info/LICENSE
DicksonUI-2.4.5.dist-info/METADATA
DicksonUI-2.4.5.dist-info/WHEEL
DicksonUI-2.4.5.dist-info/top_level.txt
DicksonUI-2.4.5.dist-info/RECORD
